{
  "sounds": [
    {
      "id": "1",
      "name": "Emotional Damage",
      "image": "https://ih1.redbubble.net/image.3180036768.2143/raf,360x360,075,t,fafafa:ca443f4786.jpg",
      "audio": "/sounds/EmotionalDamage.mp3",
      "clicks": 23
    },
    {
      "id": "2",
      "name": "3motional Damage",
      "image": "https://ih1.redbubble.net/image.5138873985.1903/bg,f8f8f8-flat,750x,075,f-pad,750x1000,f8f8f8.jpg",
      "audio": "/sounds/EmotionalDamage.mp3",
      "clicks": 6
    },
    {
      "id": "3",
      "name": "Emotional Damage",
      "image": "https://i.redd.it/xzn41f3d6qfb1.jpg",
      "audio": "/sounds/EmotionalDamage.mp3",
      "clicks": 26
    },
    {
      "id": "4",
      "name": "Emotional Damage",
      "image": "https://i.redd.it/xzn41f3d6qfb1.jpg",
      "audio": "/sounds/EmotionalDamage.mp3",
      "clicks": 0
    },
    {
      "id": "5",
      "name": "Emotional Damage",
      "image": "https://i.redd.it/xzn41f3d6qfb1.jpg",
      "audio": "/sounds/EmotionalDamage.mp3",
      "clicks": 5
    },
    {
      "id": "6",
      "name": "Emotional Damage",
      "image": "https://i.redd.it/xzn41f3d6qfb1.jpg",
      "audio": "/sounds/EmotionalDamage.mp3",
      "clicks": 6
    },
    {
      "id": "7",
      "name": "Emotional Damage",
      "image": "https://i.redd.it/xzn41f3d6qfb1.jpg",
      "audio": "/sounds/EmotionalDamage.mp3",
      "clicks": 7
    },
    {
      "id": "8",
      "name": "Emotional Damage",
      "image": "https://i.redd.it/xzn41f3d6qfb1.jpg",
      "audio": "/sounds/EmotionalDamage.mp3",
      "clicks": 0
    },
    {
      "id": "9",
      "name": "Emotional Damage",
      "image": "https://i.redd.it/xzn41f3d6qfb1.jpg",
      "audio": "/sounds/EmotionalDamage.mp3",
      "clicks": 0
    },
    {
      "id": "10",
      "name": "Emotional Damage",
      "image": "https://i.redd.it/xzn41f3d6qfb1.jpg",
      "audio": "/sounds/EmotionalDamage.mp3",
      "clicks": 0
    },
    {
      "id": "11",
      "name": "Emotional Damage",
      "image": "https://i.redd.it/xzn41f3d6qfb1.jpg",
      "audio": "/sounds/EmotionalDamage.mp3",
      "clicks": 52
    },
    {
      "id": "12",
      "name": "Emotional Damage",
      "image": "https://i.redd.it/xzn41f3d6qfb1.jpg",
      "audio": "/sounds/EmotionalDamage.mp3",
      "clicks": 3
    }
  ],
  "comments": [
    {
      "id": "46e9",
      "comment": "Yoooo Nihar that car is dope dude!",
      "user": "Kyle"
    },
    {
      "id": "d29e",
      "comment": "You got that vroom vroom pow",
      "user": "Fergie"
    },
    {
      "id": "282a",
      "comment": "How many turbos does that beauty have??",
      "user": "Stove"
    }
  ]
}